pyams_table/__init__.py
pyams_table/batch.py
pyams_table/column.py
pyams_table/header.py
pyams_table/include.py
pyams_table/interfaces.py
pyams_table/selector.py
pyams_table/table.py
pyams_table/testing.py
pyams_table/value.py
pyams_table/doctests/README.rst
pyams_table/doctests/batch.rst
pyams_table/doctests/column.rst
pyams_table/doctests/miscellaneous.rst
pyams_table/doctests/sequence.rst
pyams_table/doctests/sort.rst
pyams_table/locales/pyams_table.pot
pyams_table/locales/fr/LC_MESSAGES/pyams_table.mo
pyams_table/locales/fr/LC_MESSAGES/pyams_table.po
pyams_table/tests/__init__.py
pyams_table/tests/test_utilsdocs.py
pyams_table/tests/test_utilsdocstrings.py
pyams_table-2.0.2.dist-info/LICENSE
pyams_table-2.0.2.dist-info/METADATA
pyams_table-2.0.2.dist-info/WHEEL
pyams_table-2.0.2.dist-info/namespace_packages.txt
pyams_table-2.0.2.dist-info/top_level.txt
pyams_table-2.0.2.dist-info/RECORD
