Metadata-Version: 2.1
Name: pyams-table
Version: 2.0.2
Summary: PyAMS management package for HTML tables
Home-page: https://pyams.readthedocs.io
Author: Thierry Florac
Author-email: tflorac@ulthar.net
License: ZPL
Keywords: Pyramid PyAMS
Classifier: License :: OSI Approved :: Zope Public License
Classifier: Development Status :: 4 - Beta
Classifier: Programming Language :: Python
Classifier: Framework :: Pyramid
Classifier: Topic :: Software Development :: Libraries :: Python Modules
Requires-Python: >=3.7
License-File: LICENSE
Requires-Dist: setuptools
Requires-Dist: pyams-batching
Requires-Dist: pyams-utils
Requires-Dist: pyramid >=2.0.0
Requires-Dist: zope.component
Requires-Dist: zope.container
Requires-Dist: zope.contentprovider
Requires-Dist: zope.dublincore
Requires-Dist: zope.interface
Requires-Dist: zope.location
Requires-Dist: zope.schema
Requires-Dist: zope.security
Provides-Extra: test
